webpack_loader_remote/__init__.py
webpack_loader_remote/apps.py
webpack_loader_remote/config.py
webpack_loader_remote/errors.py
webpack_loader_remote/exceptions.py
webpack_loader_remote/loader.py
webpack_loader_remote/signals.py
webpack_loader_remote/utils.py
webpack_loader_remote/contrib/__init__.py
webpack_loader_remote/contrib/jinja2ext.py
webpack_loader_remote/templatetags/__init__.py
webpack_loader_remote/templatetags/webpack_loader.py
webpack_loader_remote-0.1.1.dist-info/LICENSE.txt
webpack_loader_remote-0.1.1.dist-info/METADATA
webpack_loader_remote-0.1.1.dist-info/WHEEL
webpack_loader_remote-0.1.1.dist-info/top_level.txt
webpack_loader_remote-0.1.1.dist-info/RECORD
