Metadata-Version: 2.1
Name: webpack-loader-remote
Version: 0.1.1
Summary: Load webpack stats from a local or remote file
Home-page: https://github.com/alexseitsinger/webpack_loader_remote
Author: Alex Seitsinger
Author-email: contact@alexseitsinger.com
License: MIT License
Keywords: django,webpack
Platform: UNKNOWN
Classifier: Programming Language :: Python :: 3
Classifier: Framework :: Django
Classifier: Environment :: Web Environment
Classifier: License :: OSI Approved :: MIT License
Requires-Dist: requests
